hag/__init__.py
hag/__main__.py
hag/displays/__init__.py
hag/displays/_base.py
hag/displays/json.py
hag/displays/roff.py
hag/displays/text.py
hag/parsers/__init__.py
hag/parsers/_base.py
hag/parsers/alacritty.py
hag/parsers/bash.py
hag/parsers/gimp.py
hag/parsers/inkscape.py
hag/parsers/lf.py
hag/parsers/mpv.py
hag/parsers/neovim.py
hag/parsers/qutebrowser.py
hag/parsers/rofi.py
hag/parsers/sioyek.py
hag/parsers/sources/__init__.py
hag/parsers/sources/_base.py
hag/parsers/sources/command.py
hag/parsers/sources/file.py
hag/parsers/sources/man_page.py
hag/parsers/sources/python_module.py
hag/parsers/sources/web_page.py
hag/parsers/sxhkd.py
hag/parsers/sxiv.py
hag/parsers/termite.py
hag/parsers/vim.py
hag/parsers/vimiv.py
hag/parsers/zathura.py
hag/parsers/zsh.py
hag/type_specs.py
hag-0.4.0.dist-info/LICENSE
hag-0.4.0.dist-info/METADATA
hag-0.4.0.dist-info/WHEEL
hag-0.4.0.dist-info/entry_points.txt
hag-0.4.0.dist-info/RECORD
