Metadata-Version: 2.1
Name: hag
Version: 0.4.0
Summary: A hotkey aggregator. All your hotkeys in one place.
Home-page: https://github.com/loiccoyle/hag
License: MIT
Keywords: hotkey,aggregator,cli
Author: Loic Coyle
Author-email: loic.coyle@hotmail.fr
Requires-Python: >=3.7,<4.0
Classifier: License :: OSI Approved :: MIT License
Classifier: Operating System :: Unix
Classifier: Programming Language :: Python
Classifier: Programming Language :: Python :: 3
Classifier: Programming Language :: Python :: 3.7
Classifier: Programming Language :: Python :: 3.8
Classifier: Programming Language :: Python :: 3.9
Classifier: Programming Language :: Python :: 3.10
Classifier: Programming Language :: Python :: 3.11
Classifier: Topic :: Utilities
Provides-Extra: alacritty
Provides-Extra: all
Provides-Extra: mpv
Provides-Extra: neovim
Requires-Dist: pynvim (>=0.4.3,<0.5.0) ; extra == "neovim" or extra == "all"
Requires-Dist: python-mpv (>=1.0.1,<2.0.0) ; extra == "mpv" or extra == "all"
Requires-Dist: pyyaml (>=6.0,<7.0) ; extra == "alacritty" or extra == "all"
Project-URL: Repository, https://github.com/loiccoyle/hag
